_iatransfer_setup/__init__.py
_iatransfer_setup/utils.py
iatransfer/__init__.py
iatransfer/research/__init__.py
iatransfer/research/runner.py
iatransfer/research/utils.py
iatransfer/research/data/__init__.py
iatransfer/research/data/data.py
iatransfer/research/data/fgvc_aircraft.py
iatransfer/research/data/flowers.py
iatransfer/research/data/food101.py
iatransfer/research/metrics/__init__.py
iatransfer/research/metrics/stats_reporter.py
iatransfer/research/models/__init__.py
iatransfer/research/models/cifar10_resnet.py
iatransfer/research/paper/__init__.py
iatransfer/research/paper/matching_vis.py
iatransfer/research/paper/plots.py
iatransfer/research/paper/sim.py
iatransfer/research/paper/statistical_tests.py
iatransfer/research/paper/stats.py
iatransfer/research/paper/table.py
iatransfer/research/paper/utils.py
iatransfer/research/train/__init__.py
iatransfer/research/train/pretrain_models.py
iatransfer/research/train/train_model.py
iatransfer/research/transfer/__init__.py
iatransfer/research/transfer/eval_transfer.py
iatransfer/research/transfer/utils.py
iatransfer/toolkit/__init__.py
iatransfer/toolkit/base_matching.py
iatransfer/toolkit/base_score.py
iatransfer/toolkit/base_standardization.py
iatransfer/toolkit/base_transfer.py
iatransfer/toolkit/iat.py
iatransfer/toolkit/tli.py
iatransfer/toolkit/tli_helpers.py
iatransfer/toolkit/matching/__init__.py
iatransfer/toolkit/matching/bipartite_matching.py
iatransfer/toolkit/matching/dp_flat_matching.py
iatransfer/toolkit/matching/dp_matching.py
iatransfer/toolkit/matching/graph_matching.py
iatransfer/toolkit/matching/nbipartite_matching.py
iatransfer/toolkit/matching/random_matching.py
iatransfer/toolkit/score/__init__.py
iatransfer/toolkit/score/autoencoder_score.py
iatransfer/toolkit/score/shape_score.py
iatransfer/toolkit/standardization/__init__.py
iatransfer/toolkit/standardization/blocks_standardization.py
iatransfer/toolkit/standardization/flatten_standardization.py
iatransfer_research-1.0.3.dist-info/LICENSE
iatransfer_research-1.0.3.dist-info/METADATA
iatransfer_research-1.0.3.dist-info/WHEEL
iatransfer_research-1.0.3.dist-info/entry_points.txt
iatransfer_research-1.0.3.dist-info/top_level.txt
iatransfer_research-1.0.3.dist-info/RECORD
