Metadata-Version: 2.1
Name: iatransfer-research
Version: 1.0.3
Summary: Tool for inter-architecture weight transfer
Home-page: https://github.com/KamilPiechowiak/weights-transfer
Author: Kamil Piechowiak, Daniel Nowak, Maciej Czyżewski
Author-email: 
License: Apache-2.0
Keywords: transfer,learning,transfer learning,training,neural network,interarchitecture
Platform: UNKNOWN
Classifier: Programming Language :: Python :: 3
Classifier: Operating System :: POSIX :: Linux
Requires-Dist: efficientnet-pytorch (>=0.7.0)
Requires-Dist: timm (>=0.3.3)
Requires-Dist: graphviz (>=0.16)
